{
	"version": 1,
	"directus": "11.8.0",
	"vendor": "postgres",
	"collections": [
		{
			"collection": "cm",
			"meta": {
				"accountability": "all",
				"archive_app_filter": true,
				"archive_field": null,
				"archive_value": "archived",
				"collapse": "open",
				"collection": "cm",
				"color": null,
				"display_template": null,
				"group": "process",
				"hidden": false,
				"icon": null,
				"item_duplication_fields": null,
				"note": null,
				"preview_url": null,
				"singleton": false,
				"sort": 1,
				"sort_field": null,
				"translations": null,
				"unarchive_value": "draft",
				"versioning": false
			},
			"schema": {
				"name": "cm"
			}
		},
		{
			"collection": "process",
			"meta": {
				"accountability": "all",
				"archive_app_filter": true,
				"archive_field": null,
				"archive_value": null,
				"collapse": "open",
				"collection": "process",
				"color": null,
				"display_template": null,
				"group": null,
				"hidden": false,
				"icon": "process_chart",
				"item_duplication_fields": null,
				"note": null,
				"preview_url": null,
				"singleton": false,
				"sort": 1,
				"sort_field": null,
				"translations": null,
				"unarchive_value": null,
				"versioning": false
			},
			"schema": {
				"name": "process"
			}
		},
		{
			"collection": "process_status",
			"meta": {
				"accountability": "all",
				"archive_app_filter": true,
				"archive_field": null,
				"archive_value": null,
				"collapse": "open",
				"collection": "process_status",
				"color": null,
				"display_template": null,
				"group": "references",
				"hidden": false,
				"icon": null,
				"item_duplication_fields": null,
				"note": null,
				"preview_url": null,
				"singleton": false,
				"sort": 1,
				"sort_field": null,
				"translations": null,
				"unarchive_value": null,
				"versioning": false
			},
			"schema": {
				"name": "process_status"
			}
		},
		{
			"collection": "references",
			"meta": {
				"accountability": "all",
				"archive_app_filter": true,
				"archive_field": null,
				"archive_value": null,
				"collapse": "open",
				"collection": "references",
				"color": null,
				"display_template": null,
				"group": null,
				"hidden": false,
				"icon": "folder",
				"item_duplication_fields": null,
				"note": null,
				"preview_url": null,
				"singleton": false,
				"sort": 3,
				"sort_field": null,
				"translations": null,
				"unarchive_value": null,
				"versioning": false
			}
		},
		{
			"collection": "task",
			"meta": {
				"accountability": "all",
				"archive_app_filter": true,
				"archive_field": null,
				"archive_value": null,
				"collapse": "open",
				"collection": "task",
				"color": null,
				"display_template": null,
				"group": null,
				"hidden": false,
				"icon": "task",
				"item_duplication_fields": null,
				"note": null,
				"preview_url": null,
				"singleton": false,
				"sort": 2,
				"sort_field": null,
				"translations": null,
				"unarchive_value": null,
				"versioning": false
			},
			"schema": {
				"name": "task"
			}
		},
		{
			"collection": "task_status",
			"meta": {
				"accountability": "all",
				"archive_app_filter": true,
				"archive_field": null,
				"archive_value": null,
				"collapse": "open",
				"collection": "task_status",
				"color": null,
				"display_template": null,
				"group": "references",
				"hidden": false,
				"icon": null,
				"item_duplication_fields": null,
				"note": null,
				"preview_url": null,
				"singleton": false,
				"sort": 2,
				"sort_field": null,
				"translations": null,
				"unarchive_value": null,
				"versioning": false
			},
			"schema": {
				"name": "task_status"
			}
		},
		{
			"collection": "user_profile",
			"meta": {
				"accountability": "all",
				"archive_app_filter": true,
				"archive_field": null,
				"archive_value": null,
				"collapse": "open",
				"collection": "user_profile",
				"color": null,
				"display_template": null,
				"group": null,
				"hidden": false,
				"icon": "supervised_user_circle",
				"item_duplication_fields": null,
				"note": null,
				"preview_url": null,
				"singleton": false,
				"sort": null,
				"sort_field": null,
				"translations": null,
				"unarchive_value": null,
				"versioning": false
			},
			"schema": {
				"name": "user_profile"
			}
		}
	],
	"fields": [
		{
			"collection": "cm",
			"field": "id",
			"type": "integer",
			"meta": {
				"collection": "cm",
				"conditions": null,
				"display": null,
				"display_options": null,
				"field": "id",
				"group": null,
				"hidden": true,
				"interface": "input",
				"note": null,
				"options": null,
				"readonly": true,
				"required": false,
				"sort": 1,
				"special": null,
				"translations": null,
				"validation": null,
				"validation_message": null,
				"width": "full"
			},
			"schema": {
				"name": "id",
				"table": "cm",
				"data_type": "integer",
				"default_value": "nextval('cm_id_seq'::regclass)",
				"max_length": null,
				"numeric_precision": 32,
				"numeric_scale": 0,
				"is_nullable": false,
				"is_unique": true,
				"is_indexed": false,
				"is_primary_key": true,
				"is_generated": false,
				"generation_expression": null,
				"has_auto_increment": true,
				"foreign_key_table": null,
				"foreign_key_column": null
			}
		},
		{
			"collection": "cm",
			"field": "user_created",
			"type": "uuid",
			"meta": {
				"collection": "cm",
				"conditions": null,
				"display": "user",
				"display_options": null,
				"field": "user_created",
				"group": null,
				"hidden": true,
				"interface": "select-dropdown-m2o",
				"note": null,
				"options": {
					"template": "{{avatar}} {{first_name}} {{last_name}}"
				},
				"readonly": true,
				"required": false,
				"sort": 2,
				"special": [
					"user-created"
				],
				"translations": null,
				"validation": null,
				"validation_message": null,
				"width": "half"
			},
			"schema": {
				"name": "user_created",
				"table": "cm",
				"data_type": "uuid",
				"default_value": null,
				"max_length": null,
				"numeric_precision": null,
				"numeric_scale": null,
				"is_nullable": true,
				"is_unique": false,
				"is_indexed": false,
				"is_primary_key": false,
				"is_generated": false,
				"generation_expression": null,
				"has_auto_increment": false,
				"foreign_key_table": "directus_users",
				"foreign_key_column": "id"
			}
		},
		{
			"collection": "cm",
			"field": "date_created",
			"type": "timestamp",
			"meta": {
				"collection": "cm",
				"conditions": null,
				"display": "datetime",
				"display_options": {
					"relative": true
				},
				"field": "date_created",
				"group": null,
				"hidden": true,
				"interface": "datetime",
				"note": null,
				"options": null,
				"readonly": true,
				"required": false,
				"sort": 3,
				"special": [
					"date-created"
				],
				"translations": null,
				"validation": null,
				"validation_message": null,
				"width": "half"
			},
			"schema": {
				"name": "date_created",
				"table": "cm",
				"data_type": "timestamp with time zone",
				"default_value": null,
				"max_length": null,
				"numeric_precision": null,
				"numeric_scale": null,
				"is_nullable": true,
				"is_unique": false,
				"is_indexed": false,
				"is_primary_key": false,
				"is_generated": false,
				"generation_expression": null,
				"has_auto_increment": false,
				"foreign_key_table": null,
				"foreign_key_column": null
			}
		},
		{
			"collection": "cm",
			"field": "user_updated",
			"type": "uuid",
			"meta": {
				"collection": "cm",
				"conditions": null,
				"display": "user",
				"display_options": null,
				"field": "user_updated",
				"group": null,
				"hidden": true,
				"interface": "select-dropdown-m2o",
				"note": null,
				"options": {
					"template": "{{avatar}} {{first_name}} {{last_name}}"
				},
				"readonly": true,
				"required": false,
				"sort": 4,
				"special": [
					"user-updated"
				],
				"translations": null,
				"validation": null,
				"validation_message": null,
				"width": "half"
			},
			"schema": {
				"name": "user_updated",
				"table": "cm",
				"data_type": "uuid",
				"default_value": null,
				"max_length": null,
				"numeric_precision": null,
				"numeric_scale": null,
				"is_nullable": true,
				"is_unique": false,
				"is_indexed": false,
				"is_primary_key": false,
				"is_generated": false,
				"generation_expression": null,
				"has_auto_increment": false,
				"foreign_key_table": "directus_users",
				"foreign_key_column": "id"
			}
		},
		{
			"collection": "cm",
			"field": "date_updated",
			"type": "timestamp",
			"meta": {
				"collection": "cm",
				"conditions": null,
				"display": "datetime",
				"display_options": {
					"relative": true
				},
				"field": "date_updated",
				"group": null,
				"hidden": true,
				"interface": "datetime",
				"note": null,
				"options": null,
				"readonly": true,
				"required": false,
				"sort": 5,
				"special": [
					"date-updated"
				],
				"translations": null,
				"validation": null,
				"validation_message": null,
				"width": "half"
			},
			"schema": {
				"name": "date_updated",
				"table": "cm",
				"data_type": "timestamp with time zone",
				"default_value": null,
				"max_length": null,
				"numeric_precision": null,
				"numeric_scale": null,
				"is_nullable": true,
				"is_unique": false,
				"is_indexed": false,
				"is_primary_key": false,
				"is_generated": false,
				"generation_expression": null,
				"has_auto_increment": false,
				"foreign_key_table": null,
				"foreign_key_column": null
			}
		},
		{
			"collection": "cm",
			"field": "name",
			"type": "string",
			"meta": {
				"collection": "cm",
				"conditions": null,
				"display": null,
				"display_options": null,
				"field": "name",
				"group": null,
				"hidden": false,
				"interface": "input",
				"note": null,
				"options": null,
				"readonly": false,
				"required": false,
				"sort": 6,
				"special": null,
				"translations": null,
				"validation": null,
				"validation_message": null,
				"width": "half"
			},
			"schema": {
				"name": "name",
				"table": "cm",
				"data_type": "character varying",
				"default_value": null,
				"max_length": 255,
				"numeric_precision": null,
				"numeric_scale": null,
				"is_nullable": true,
				"is_unique": false,
				"is_indexed": false,
				"is_primary_key": false,
				"is_generated": false,
				"generation_expression": null,
				"has_auto_increment": false,
				"foreign_key_table": null,
				"foreign_key_column": null
			}
		},
		{
			"collection": "cm",
			"field": "desc",
			"type": "text",
			"meta": {
				"collection": "cm",
				"conditions": null,
				"display": null,
				"display_options": null,
				"field": "desc",
				"group": null,
				"hidden": false,
				"interface": "input-multiline",
				"note": null,
				"options": null,
				"readonly": false,
				"required": false,
				"sort": 11,
				"special": null,
				"translations": null,
				"validation": null,
				"validation_message": null,
				"width": "full"
			},
			"schema": {
				"name": "desc",
				"table": "cm",
				"data_type": "text",
				"default_value": null,
				"max_length": null,
				"numeric_precision": null,
				"numeric_scale": null,
				"is_nullable": true,
				"is_unique": false,
				"is_indexed": false,
				"is_primary_key": false,
				"is_generated": false,
				"generation_expression": null,
				"has_auto_increment": false,
				"foreign_key_table": null,
				"foreign_key_column": null
			}
		},
		{
			"collection": "cm",
			"field": "responsible",
			"type": "uuid",
			"meta": {
				"collection": "cm",
				"conditions": null,
				"display": null,
				"display_options": null,
				"field": "responsible",
				"group": null,
				"hidden": false,
				"interface": "select-dropdown-m2o",
				"note": null,
				"options": {
					"enableCreate": false,
					"template": "{{first_name}} {{last_name}}"
				},
				"readonly": false,
				"required": false,
				"sort": 8,
				"special": [
					"m2o"
				],
				"translations": null,
				"validation": null,
				"validation_message": null,
				"width": "half"
			},
			"schema": {
				"name": "responsible",
				"table": "cm",
				"data_type": "uuid",
				"default_value": null,
				"max_length": null,
				"numeric_precision": null,
				"numeric_scale": null,
				"is_nullable": true,
				"is_unique": false,
				"is_indexed": false,
				"is_primary_key": false,
				"is_generated": false,
				"generation_expression": null,
				"has_auto_increment": false,
				"foreign_key_table": "directus_users",
				"foreign_key_column": "id"
			}
		},
		{
			"collection": "cm",
			"field": "due_date",
			"type": "dateTime",
			"meta": {
				"collection": "cm",
				"conditions": null,
				"display": null,
				"display_options": null,
				"field": "due_date",
				"group": null,
				"hidden": false,
				"interface": "datetime",
				"note": null,
				"options": null,
				"readonly": false,
				"required": false,
				"sort": 9,
				"special": null,
				"translations": null,
				"validation": null,
				"validation_message": null,
				"width": "half"
			},
			"schema": {
				"name": "due_date",
				"table": "cm",
				"data_type": "timestamp without time zone",
				"default_value": null,
				"max_length": null,
				"numeric_precision": null,
				"numeric_scale": null,
				"is_nullable": true,
				"is_unique": false,
				"is_indexed": false,
				"is_primary_key": false,
				"is_generated": false,
				"generation_expression": null,
				"has_auto_increment": false,
				"foreign_key_table": null,
				"foreign_key_column": null
			}
		},
		{
			"collection": "cm",
			"field": "process",
			"type": "uuid",
			"meta": {
				"collection": "cm",
				"conditions": null,
				"display": null,
				"display_options": null,
				"field": "process",
				"group": null,
				"hidden": false,
				"interface": "select-dropdown-m2o",
				"note": null,
				"options": {
					"template": "{{name}}"
				},
				"readonly": false,
				"required": false,
				"sort": 7,
				"special": [
					"m2o"
				],
				"translations": null,
				"validation": null,
				"validation_message": null,
				"width": "half"
			},
			"schema": {
				"name": "process",
				"table": "cm",
				"data_type": "uuid",
				"default_value": "50558a56-e136-4b47-a187-97241ade0546",
				"max_length": null,
				"numeric_precision": null,
				"numeric_scale": null,
				"is_nullable": true,
				"is_unique": false,
				"is_indexed": false,
				"is_primary_key": false,
				"is_generated": false,
				"generation_expression": null,
				"has_auto_increment": false,
				"foreign_key_table": "process",
				"foreign_key_column": "id"
			}
		},
		{
			"collection": "cm",
			"field": "status",
			"type": "integer",
			"meta": {
				"collection": "cm",
				"conditions": null,
				"display": null,
				"display_options": null,
				"field": "status",
				"group": null,
				"hidden": false,
				"interface": "select-dropdown-m2o",
				"note": null,
				"options": {
					"template": "{{name}}"
				},
				"readonly": false,
				"required": false,
				"sort": 10,
				"special": [
					"m2o"
				],
				"translations": null,
				"validation": null,
				"validation_message": null,
				"width": "full"
			},
			"schema": {
				"name": "status",
				"table": "cm",
				"data_type": "integer",
				"default_value": 1,
				"max_length": null,
				"numeric_precision": 32,
				"numeric_scale": 0,
				"is_nullable": true,
				"is_unique": false,
				"is_indexed": false,
				"is_primary_key": false,
				"is_generated": false,
				"generation_expression": null,
				"has_auto_increment": false,
				"foreign_key_table": "process_status",
				"foreign_key_column": "id"
			}
		},
		{
			"collection": "process",
			"field": "id",
			"type": "uuid",
			"meta": {
				"collection": "process",
				"conditions": null,
				"display": null,
				"display_options": null,
				"field": "id",
				"group": null,
				"hidden": true,
				"interface": "input",
				"note": null,
				"options": null,
				"readonly": true,
				"required": false,
				"sort": 1,
				"special": [
					"uuid"
				],
				"translations": null,
				"validation": null,
				"validation_message": null,
				"width": "full"
			},
			"schema": {
				"name": "id",
				"table": "process",
				"data_type": "uuid",
				"default_value": null,
				"max_length": null,
				"numeric_precision": null,
				"numeric_scale": null,
				"is_nullable": false,
				"is_unique": true,
				"is_indexed": false,
				"is_primary_key": true,
				"is_generated": false,
				"generation_expression": null,
				"has_auto_increment": false,
				"foreign_key_table": null,
				"foreign_key_column": null
			}
		},
		{
			"collection": "process",
			"field": "name",
			"type": "string",
			"meta": {
				"collection": "process",
				"conditions": null,
				"display": null,
				"display_options": null,
				"field": "name",
				"group": null,
				"hidden": false,
				"interface": "input",
				"note": null,
				"options": null,
				"readonly": false,
				"required": false,
				"sort": 2,
				"special": null,
				"translations": null,
				"validation": null,
				"validation_message": null,
				"width": "half"
			},
			"schema": {
				"name": "name",
				"table": "process",
				"data_type": "character varying",
				"default_value": null,
				"max_length": 255,
				"numeric_precision": null,
				"numeric_scale": null,
				"is_nullable": true,
				"is_unique": false,
				"is_indexed": false,
				"is_primary_key": false,
				"is_generated": false,
				"generation_expression": null,
				"has_auto_increment": false,
				"foreign_key_table": null,
				"foreign_key_column": null
			}
		},
		{
			"collection": "process",
			"field": "name_en",
			"type": "string",
			"meta": {
				"collection": "process",
				"conditions": null,
				"display": null,
				"display_options": null,
				"field": "name_en",
				"group": null,
				"hidden": false,
				"interface": "input",
				"note": null,
				"options": null,
				"readonly": false,
				"required": false,
				"sort": 3,
				"special": null,
				"translations": null,
				"validation": null,
				"validation_message": null,
				"width": "half"
			},
			"schema": {
				"name": "name_en",
				"table": "process",
				"data_type": "character varying",
				"default_value": null,
				"max_length": 255,
				"numeric_precision": null,
				"numeric_scale": null,
				"is_nullable": true,
				"is_unique": false,
				"is_indexed": false,
				"is_primary_key": false,
				"is_generated": false,
				"generation_expression": null,
				"has_auto_increment": false,
				"foreign_key_table": null,
				"foreign_key_column": null
			}
		},
		{
			"collection": "process",
			"field": "url",
			"type": "string",
			"meta": {
				"collection": "process",
				"conditions": null,
				"display": null,
				"display_options": null,
				"field": "url",
				"group": null,
				"hidden": false,
				"interface": "input",
				"note": null,
				"options": null,
				"readonly": false,
				"required": false,
				"sort": 4,
				"special": null,
				"translations": null,
				"validation": null,
				"validation_message": null,
				"width": "full"
			},
			"schema": {
				"name": "url",
				"table": "process",
				"data_type": "character varying",
				"default_value": null,
				"max_length": 255,
				"numeric_precision": null,
				"numeric_scale": null,
				"is_nullable": true,
				"is_unique": false,
				"is_indexed": false,
				"is_primary_key": false,
				"is_generated": false,
				"generation_expression": null,
				"has_auto_increment": false,
				"foreign_key_table": null,
				"foreign_key_column": null
			}
		},
		{
			"collection": "process_status",
			"field": "id",
			"type": "integer",
			"meta": {
				"collection": "process_status",
				"conditions": null,
				"display": null,
				"display_options": null,
				"field": "id",
				"group": null,
				"hidden": true,
				"interface": "input",
				"note": null,
				"options": null,
				"readonly": true,
				"required": false,
				"sort": 1,
				"special": null,
				"translations": null,
				"validation": null,
				"validation_message": null,
				"width": "full"
			},
			"schema": {
				"name": "id",
				"table": "process_status",
				"data_type": "integer",
				"default_value": "nextval('process_status_id_seq'::regclass)",
				"max_length": null,
				"numeric_precision": 32,
				"numeric_scale": 0,
				"is_nullable": false,
				"is_unique": true,
				"is_indexed": false,
				"is_primary_key": true,
				"is_generated": false,
				"generation_expression": null,
				"has_auto_increment": true,
				"foreign_key_table": null,
				"foreign_key_column": null
			}
		},
		{
			"collection": "process_status",
			"field": "name",
			"type": "string",
			"meta": {
				"collection": "process_status",
				"conditions": null,
				"display": null,
				"display_options": null,
				"field": "name",
				"group": null,
				"hidden": false,
				"interface": "input",
				"note": null,
				"options": null,
				"readonly": false,
				"required": false,
				"sort": 2,
				"special": null,
				"translations": null,
				"validation": null,
				"validation_message": null,
				"width": "half"
			},
			"schema": {
				"name": "name",
				"table": "process_status",
				"data_type": "character varying",
				"default_value": null,
				"max_length": 255,
				"numeric_precision": null,
				"numeric_scale": null,
				"is_nullable": true,
				"is_unique": false,
				"is_indexed": false,
				"is_primary_key": false,
				"is_generated": false,
				"generation_expression": null,
				"has_auto_increment": false,
				"foreign_key_table": null,
				"foreign_key_column": null
			}
		},
		{
			"collection": "process_status",
			"field": "name_en",
			"type": "string",
			"meta": {
				"collection": "process_status",
				"conditions": null,
				"display": null,
				"display_options": null,
				"field": "name_en",
				"group": null,
				"hidden": false,
				"interface": "input",
				"note": null,
				"options": null,
				"readonly": false,
				"required": false,
				"sort": 3,
				"special": null,
				"translations": null,
				"validation": null,
				"validation_message": null,
				"width": "half"
			},
			"schema": {
				"name": "name_en",
				"table": "process_status",
				"data_type": "character varying",
				"default_value": null,
				"max_length": 255,
				"numeric_precision": null,
				"numeric_scale": null,
				"is_nullable": true,
				"is_unique": false,
				"is_indexed": false,
				"is_primary_key": false,
				"is_generated": false,
				"generation_expression": null,
				"has_auto_increment": false,
				"foreign_key_table": null,
				"foreign_key_column": null
			}
		},
		{
			"collection": "task",
			"field": "id",
			"type": "uuid",
			"meta": {
				"collection": "task",
				"conditions": null,
				"display": null,
				"display_options": null,
				"field": "id",
				"group": null,
				"hidden": true,
				"interface": "input",
				"note": null,
				"options": null,
				"readonly": true,
				"required": false,
				"sort": 1,
				"special": [
					"uuid"
				],
				"translations": null,
				"validation": null,
				"validation_message": null,
				"width": "full"
			},
			"schema": {
				"name": "id",
				"table": "task",
				"data_type": "uuid",
				"default_value": null,
				"max_length": null,
				"numeric_precision": null,
				"numeric_scale": null,
				"is_nullable": false,
				"is_unique": true,
				"is_indexed": false,
				"is_primary_key": true,
				"is_generated": false,
				"generation_expression": null,
				"has_auto_increment": false,
				"foreign_key_table": null,
				"foreign_key_column": null
			}
		},
		{
			"collection": "task",
			"field": "user_created",
			"type": "uuid",
			"meta": {
				"collection": "task",
				"conditions": null,
				"display": "user",
				"display_options": null,
				"field": "user_created",
				"group": null,
				"hidden": true,
				"interface": "select-dropdown-m2o",
				"note": null,
				"options": {
					"template": "{{avatar}} {{first_name}} {{last_name}}"
				},
				"readonly": true,
				"required": false,
				"sort": 2,
				"special": [
					"user-created"
				],
				"translations": null,
				"validation": null,
				"validation_message": null,
				"width": "half"
			},
			"schema": {
				"name": "user_created",
				"table": "task",
				"data_type": "uuid",
				"default_value": null,
				"max_length": null,
				"numeric_precision": null,
				"numeric_scale": null,
				"is_nullable": true,
				"is_unique": false,
				"is_indexed": false,
				"is_primary_key": false,
				"is_generated": false,
				"generation_expression": null,
				"has_auto_increment": false,
				"foreign_key_table": "directus_users",
				"foreign_key_column": "id"
			}
		},
		{
			"collection": "task",
			"field": "date_created",
			"type": "timestamp",
			"meta": {
				"collection": "task",
				"conditions": null,
				"display": "datetime",
				"display_options": {
					"relative": true
				},
				"field": "date_created",
				"group": null,
				"hidden": true,
				"interface": "datetime",
				"note": null,
				"options": null,
				"readonly": true,
				"required": false,
				"sort": 3,
				"special": [
					"date-created"
				],
				"translations": null,
				"validation": null,
				"validation_message": null,
				"width": "half"
			},
			"schema": {
				"name": "date_created",
				"table": "task",
				"data_type": "timestamp with time zone",
				"default_value": null,
				"max_length": null,
				"numeric_precision": null,
				"numeric_scale": null,
				"is_nullable": true,
				"is_unique": false,
				"is_indexed": false,
				"is_primary_key": false,
				"is_generated": false,
				"generation_expression": null,
				"has_auto_increment": false,
				"foreign_key_table": null,
				"foreign_key_column": null
			}
		},
		{
			"collection": "task",
			"field": "user_updated",
			"type": "uuid",
			"meta": {
				"collection": "task",
				"conditions": null,
				"display": "user",
				"display_options": null,
				"field": "user_updated",
				"group": null,
				"hidden": true,
				"interface": "select-dropdown-m2o",
				"note": null,
				"options": {
					"template": "{{avatar}} {{first_name}} {{last_name}}"
				},
				"readonly": true,
				"required": false,
				"sort": 4,
				"special": [
					"user-updated"
				],
				"translations": null,
				"validation": null,
				"validation_message": null,
				"width": "half"
			},
			"schema": {
				"name": "user_updated",
				"table": "task",
				"data_type": "uuid",
				"default_value": null,
				"max_length": null,
				"numeric_precision": null,
				"numeric_scale": null,
				"is_nullable": true,
				"is_unique": false,
				"is_indexed": false,
				"is_primary_key": false,
				"is_generated": false,
				"generation_expression": null,
				"has_auto_increment": false,
				"foreign_key_table": "directus_users",
				"foreign_key_column": "id"
			}
		},
		{
			"collection": "task",
			"field": "date_updated",
			"type": "timestamp",
			"meta": {
				"collection": "task",
				"conditions": null,
				"display": "datetime",
				"display_options": {
					"relative": true
				},
				"field": "date_updated",
				"group": null,
				"hidden": true,
				"interface": "datetime",
				"note": null,
				"options": null,
				"readonly": true,
				"required": false,
				"sort": 5,
				"special": [
					"date-updated"
				],
				"translations": null,
				"validation": null,
				"validation_message": null,
				"width": "half"
			},
			"schema": {
				"name": "date_updated",
				"table": "task",
				"data_type": "timestamp with time zone",
				"default_value": null,
				"max_length": null,
				"numeric_precision": null,
				"numeric_scale": null,
				"is_nullable": true,
				"is_unique": false,
				"is_indexed": false,
				"is_primary_key": false,
				"is_generated": false,
				"generation_expression": null,
				"has_auto_increment": false,
				"foreign_key_table": null,
				"foreign_key_column": null
			}
		},
		{
			"collection": "task",
			"field": "name",
			"type": "string",
			"meta": {
				"collection": "task",
				"conditions": null,
				"display": null,
				"display_options": null,
				"field": "name",
				"group": null,
				"hidden": false,
				"interface": "input",
				"note": null,
				"options": null,
				"readonly": false,
				"required": false,
				"sort": 6,
				"special": null,
				"translations": null,
				"validation": null,
				"validation_message": null,
				"width": "full"
			},
			"schema": {
				"name": "name",
				"table": "task",
				"data_type": "character varying",
				"default_value": null,
				"max_length": 255,
				"numeric_precision": null,
				"numeric_scale": null,
				"is_nullable": true,
				"is_unique": false,
				"is_indexed": false,
				"is_primary_key": false,
				"is_generated": false,
				"generation_expression": null,
				"has_auto_increment": false,
				"foreign_key_table": null,
				"foreign_key_column": null
			}
		},
		{
			"collection": "task",
			"field": "responsible",
			"type": "uuid",
			"meta": {
				"collection": "task",
				"conditions": null,
				"display": null,
				"display_options": null,
				"field": "responsible",
				"group": null,
				"hidden": false,
				"interface": "select-dropdown-m2o",
				"note": null,
				"options": {
					"template": "{{first_name}} {{last_name}}"
				},
				"readonly": false,
				"required": false,
				"sort": 7,
				"special": [
					"m2o"
				],
				"translations": null,
				"validation": null,
				"validation_message": null,
				"width": "half"
			},
			"schema": {
				"name": "responsible",
				"table": "task",
				"data_type": "uuid",
				"default_value": null,
				"max_length": null,
				"numeric_precision": null,
				"numeric_scale": null,
				"is_nullable": true,
				"is_unique": false,
				"is_indexed": false,
				"is_primary_key": false,
				"is_generated": false,
				"generation_expression": null,
				"has_auto_increment": false,
				"foreign_key_table": "directus_users",
				"foreign_key_column": "id"
			}
		},
		{
			"collection": "task",
			"field": "due_date",
			"type": "dateTime",
			"meta": {
				"collection": "task",
				"conditions": null,
				"display": null,
				"display_options": null,
				"field": "due_date",
				"group": null,
				"hidden": false,
				"interface": "datetime",
				"note": null,
				"options": null,
				"readonly": false,
				"required": false,
				"sort": 8,
				"special": null,
				"translations": null,
				"validation": null,
				"validation_message": null,
				"width": "half"
			},
			"schema": {
				"name": "due_date",
				"table": "task",
				"data_type": "timestamp without time zone",
				"default_value": null,
				"max_length": null,
				"numeric_precision": null,
				"numeric_scale": null,
				"is_nullable": true,
				"is_unique": false,
				"is_indexed": false,
				"is_primary_key": false,
				"is_generated": false,
				"generation_expression": null,
				"has_auto_increment": false,
				"foreign_key_table": null,
				"foreign_key_column": null
			}
		},
		{
			"collection": "task",
			"field": "process",
			"type": "uuid",
			"meta": {
				"collection": "task",
				"conditions": null,
				"display": null,
				"display_options": null,
				"field": "process",
				"group": null,
				"hidden": false,
				"interface": "select-dropdown-m2o",
				"note": null,
				"options": {
					"template": "{{name}}"
				},
				"readonly": false,
				"required": false,
				"sort": 9,
				"special": [
					"m2o"
				],
				"translations": null,
				"validation": null,
				"validation_message": null,
				"width": "half"
			},
			"schema": {
				"name": "process",
				"table": "task",
				"data_type": "uuid",
				"default_value": null,
				"max_length": null,
				"numeric_precision": null,
				"numeric_scale": null,
				"is_nullable": true,
				"is_unique": false,
				"is_indexed": false,
				"is_primary_key": false,
				"is_generated": false,
				"generation_expression": null,
				"has_auto_increment": false,
				"foreign_key_table": "process",
				"foreign_key_column": "id"
			}
		},
		{
			"collection": "task",
			"field": "type",
			"type": "string",
			"meta": {
				"collection": "task",
				"conditions": null,
				"display": null,
				"display_options": null,
				"field": "type",
				"group": null,
				"hidden": false,
				"interface": "input",
				"note": null,
				"options": null,
				"readonly": false,
				"required": false,
				"sort": 10,
				"special": null,
				"translations": null,
				"validation": null,
				"validation_message": null,
				"width": "half"
			},
			"schema": {
				"name": "type",
				"table": "task",
				"data_type": "character varying",
				"default_value": null,
				"max_length": 255,
				"numeric_precision": null,
				"numeric_scale": null,
				"is_nullable": true,
				"is_unique": false,
				"is_indexed": false,
				"is_primary_key": false,
				"is_generated": false,
				"generation_expression": null,
				"has_auto_increment": false,
				"foreign_key_table": null,
				"foreign_key_column": null
			}
		},
		{
			"collection": "task",
			"field": "context",
			"type": "string",
			"meta": {
				"collection": "task",
				"conditions": null,
				"display": null,
				"display_options": null,
				"field": "context",
				"group": null,
				"hidden": false,
				"interface": "input",
				"note": null,
				"options": null,
				"readonly": false,
				"required": false,
				"sort": 11,
				"special": null,
				"translations": null,
				"validation": null,
				"validation_message": null,
				"width": "half"
			},
			"schema": {
				"name": "context",
				"table": "task",
				"data_type": "character varying",
				"default_value": null,
				"max_length": 255,
				"numeric_precision": null,
				"numeric_scale": null,
				"is_nullable": true,
				"is_unique": false,
				"is_indexed": false,
				"is_primary_key": false,
				"is_generated": false,
				"generation_expression": null,
				"has_auto_increment": false,
				"foreign_key_table": null,
				"foreign_key_column": null
			}
		},
		{
			"collection": "task",
			"field": "status",
			"type": "integer",
			"meta": {
				"collection": "task",
				"conditions": null,
				"display": null,
				"display_options": null,
				"field": "status",
				"group": null,
				"hidden": false,
				"interface": "select-dropdown-m2o",
				"note": null,
				"options": {
					"enableCreate": false
				},
				"readonly": false,
				"required": false,
				"sort": 12,
				"special": [
					"m2o"
				],
				"translations": null,
				"validation": null,
				"validation_message": null,
				"width": "half"
			},
			"schema": {
				"name": "status",
				"table": "task",
				"data_type": "integer",
				"default_value": 1,
				"max_length": null,
				"numeric_precision": 32,
				"numeric_scale": 0,
				"is_nullable": true,
				"is_unique": false,
				"is_indexed": false,
				"is_primary_key": false,
				"is_generated": false,
				"generation_expression": null,
				"has_auto_increment": false,
				"foreign_key_table": "task_status",
				"foreign_key_column": "id"
			}
		},
		{
			"collection": "task_status",
			"field": "id",
			"type": "integer",
			"meta": {
				"collection": "task_status",
				"conditions": null,
				"display": null,
				"display_options": null,
				"field": "id",
				"group": null,
				"hidden": true,
				"interface": "input",
				"note": null,
				"options": null,
				"readonly": true,
				"required": false,
				"sort": 1,
				"special": null,
				"translations": null,
				"validation": null,
				"validation_message": null,
				"width": "full"
			},
			"schema": {
				"name": "id",
				"table": "task_status",
				"data_type": "integer",
				"default_value": "nextval('task_status_id_seq'::regclass)",
				"max_length": null,
				"numeric_precision": 32,
				"numeric_scale": 0,
				"is_nullable": false,
				"is_unique": true,
				"is_indexed": false,
				"is_primary_key": true,
				"is_generated": false,
				"generation_expression": null,
				"has_auto_increment": true,
				"foreign_key_table": null,
				"foreign_key_column": null
			}
		},
		{
			"collection": "task_status",
			"field": "name",
			"type": "string",
			"meta": {
				"collection": "task_status",
				"conditions": null,
				"display": null,
				"display_options": null,
				"field": "name",
				"group": null,
				"hidden": false,
				"interface": "input",
				"note": null,
				"options": null,
				"readonly": false,
				"required": false,
				"sort": 2,
				"special": null,
				"translations": null,
				"validation": null,
				"validation_message": null,
				"width": "half"
			},
			"schema": {
				"name": "name",
				"table": "task_status",
				"data_type": "character varying",
				"default_value": null,
				"max_length": 255,
				"numeric_precision": null,
				"numeric_scale": null,
				"is_nullable": true,
				"is_unique": false,
				"is_indexed": false,
				"is_primary_key": false,
				"is_generated": false,
				"generation_expression": null,
				"has_auto_increment": false,
				"foreign_key_table": null,
				"foreign_key_column": null
			}
		},
		{
			"collection": "task_status",
			"field": "name_en",
			"type": "string",
			"meta": {
				"collection": "task_status",
				"conditions": null,
				"display": null,
				"display_options": null,
				"field": "name_en",
				"group": null,
				"hidden": false,
				"interface": "input",
				"note": null,
				"options": null,
				"readonly": false,
				"required": false,
				"sort": 3,
				"special": null,
				"translations": null,
				"validation": null,
				"validation_message": null,
				"width": "half"
			},
			"schema": {
				"name": "name_en",
				"table": "task_status",
				"data_type": "character varying",
				"default_value": null,
				"max_length": 255,
				"numeric_precision": null,
				"numeric_scale": null,
				"is_nullable": true,
				"is_unique": false,
				"is_indexed": false,
				"is_primary_key": false,
				"is_generated": false,
				"generation_expression": null,
				"has_auto_increment": false,
				"foreign_key_table": null,
				"foreign_key_column": null
			}
		},
		{
			"collection": "user_profile",
			"field": "id",
			"type": "uuid",
			"meta": {
				"collection": "user_profile",
				"conditions": null,
				"display": null,
				"display_options": null,
				"field": "id",
				"group": null,
				"hidden": true,
				"interface": "input",
				"note": null,
				"options": null,
				"readonly": true,
				"required": false,
				"sort": 1,
				"special": [
					"uuid"
				],
				"translations": null,
				"validation": null,
				"validation_message": null,
				"width": "full"
			},
			"schema": {
				"name": "id",
				"table": "user_profile",
				"data_type": "uuid",
				"default_value": null,
				"max_length": null,
				"numeric_precision": null,
				"numeric_scale": null,
				"is_nullable": false,
				"is_unique": true,
				"is_indexed": false,
				"is_primary_key": true,
				"is_generated": false,
				"generation_expression": null,
				"has_auto_increment": false,
				"foreign_key_table": null,
				"foreign_key_column": null
			}
		},
		{
			"collection": "user_profile",
			"field": "user_created",
			"type": "uuid",
			"meta": {
				"collection": "user_profile",
				"conditions": null,
				"display": "user",
				"display_options": null,
				"field": "user_created",
				"group": null,
				"hidden": true,
				"interface": "select-dropdown-m2o",
				"note": null,
				"options": {
					"template": "{{avatar}} {{first_name}} {{last_name}}"
				},
				"readonly": true,
				"required": false,
				"sort": 2,
				"special": [
					"user-created"
				],
				"translations": null,
				"validation": null,
				"validation_message": null,
				"width": "half"
			},
			"schema": {
				"name": "user_created",
				"table": "user_profile",
				"data_type": "uuid",
				"default_value": null,
				"max_length": null,
				"numeric_precision": null,
				"numeric_scale": null,
				"is_nullable": true,
				"is_unique": false,
				"is_indexed": false,
				"is_primary_key": false,
				"is_generated": false,
				"generation_expression": null,
				"has_auto_increment": false,
				"foreign_key_table": "directus_users",
				"foreign_key_column": "id"
			}
		},
		{
			"collection": "user_profile",
			"field": "date_created",
			"type": "timestamp",
			"meta": {
				"collection": "user_profile",
				"conditions": null,
				"display": "datetime",
				"display_options": {
					"relative": true
				},
				"field": "date_created",
				"group": null,
				"hidden": true,
				"interface": "datetime",
				"note": null,
				"options": null,
				"readonly": true,
				"required": false,
				"sort": 3,
				"special": [
					"date-created"
				],
				"translations": null,
				"validation": null,
				"validation_message": null,
				"width": "half"
			},
			"schema": {
				"name": "date_created",
				"table": "user_profile",
				"data_type": "timestamp with time zone",
				"default_value": null,
				"max_length": null,
				"numeric_precision": null,
				"numeric_scale": null,
				"is_nullable": true,
				"is_unique": false,
				"is_indexed": false,
				"is_primary_key": false,
				"is_generated": false,
				"generation_expression": null,
				"has_auto_increment": false,
				"foreign_key_table": null,
				"foreign_key_column": null
			}
		},
		{
			"collection": "user_profile",
			"field": "user_updated",
			"type": "uuid",
			"meta": {
				"collection": "user_profile",
				"conditions": null,
				"display": "user",
				"display_options": null,
				"field": "user_updated",
				"group": null,
				"hidden": true,
				"interface": "select-dropdown-m2o",
				"note": null,
				"options": {
					"template": "{{avatar}} {{first_name}} {{last_name}}"
				},
				"readonly": true,
				"required": false,
				"sort": 4,
				"special": [
					"user-updated"
				],
				"translations": null,
				"validation": null,
				"validation_message": null,
				"width": "half"
			},
			"schema": {
				"name": "user_updated",
				"table": "user_profile",
				"data_type": "uuid",
				"default_value": null,
				"max_length": null,
				"numeric_precision": null,
				"numeric_scale": null,
				"is_nullable": true,
				"is_unique": false,
				"is_indexed": false,
				"is_primary_key": false,
				"is_generated": false,
				"generation_expression": null,
				"has_auto_increment": false,
				"foreign_key_table": "directus_users",
				"foreign_key_column": "id"
			}
		},
		{
			"collection": "user_profile",
			"field": "date_updated",
			"type": "timestamp",
			"meta": {
				"collection": "user_profile",
				"conditions": null,
				"display": "datetime",
				"display_options": {
					"relative": true
				},
				"field": "date_updated",
				"group": null,
				"hidden": true,
				"interface": "datetime",
				"note": null,
				"options": null,
				"readonly": true,
				"required": false,
				"sort": 5,
				"special": [
					"date-updated"
				],
				"translations": null,
				"validation": null,
				"validation_message": null,
				"width": "half"
			},
			"schema": {
				"name": "date_updated",
				"table": "user_profile",
				"data_type": "timestamp with time zone",
				"default_value": null,
				"max_length": null,
				"numeric_precision": null,
				"numeric_scale": null,
				"is_nullable": true,
				"is_unique": false,
				"is_indexed": false,
				"is_primary_key": false,
				"is_generated": false,
				"generation_expression": null,
				"has_auto_increment": false,
				"foreign_key_table": null,
				"foreign_key_column": null
			}
		},
		{
			"collection": "user_profile",
			"field": "user",
			"type": "uuid",
			"meta": {
				"collection": "user_profile",
				"conditions": null,
				"display": null,
				"display_options": null,
				"field": "user",
				"group": null,
				"hidden": false,
				"interface": "select-dropdown-m2o",
				"note": null,
				"options": {
					"enableCreate": false,
					"template": "{{last_name}} {{first_name}}"
				},
				"readonly": false,
				"required": false,
				"sort": 6,
				"special": [
					"m2o"
				],
				"translations": null,
				"validation": null,
				"validation_message": null,
				"width": "half"
			},
			"schema": {
				"name": "user",
				"table": "user_profile",
				"data_type": "uuid",
				"default_value": null,
				"max_length": null,
				"numeric_precision": null,
				"numeric_scale": null,
				"is_nullable": true,
				"is_unique": true,
				"is_indexed": false,
				"is_primary_key": false,
				"is_generated": false,
				"generation_expression": null,
				"has_auto_increment": false,
				"foreign_key_table": "directus_users",
				"foreign_key_column": "id"
			}
		},
		{
			"collection": "user_profile",
			"field": "telegram",
			"type": "string",
			"meta": {
				"collection": "user_profile",
				"conditions": null,
				"display": null,
				"display_options": null,
				"field": "telegram",
				"group": null,
				"hidden": false,
				"interface": "input",
				"note": null,
				"options": null,
				"readonly": false,
				"required": false,
				"sort": 7,
				"special": null,
				"translations": null,
				"validation": null,
				"validation_message": null,
				"width": "half"
			},
			"schema": {
				"name": "telegram",
				"table": "user_profile",
				"data_type": "character varying",
				"default_value": null,
				"max_length": 255,
				"numeric_precision": null,
				"numeric_scale": null,
				"is_nullable": true,
				"is_unique": false,
				"is_indexed": false,
				"is_primary_key": false,
				"is_generated": false,
				"generation_expression": null,
				"has_auto_increment": false,
				"foreign_key_table": null,
				"foreign_key_column": null
			}
		}
	],
	"relations": [
		{
			"collection": "cm",
			"field": "user_created",
			"related_collection": "directus_users",
			"meta": {
				"junction_field": null,
				"many_collection": "cm",
				"many_field": "user_created",
				"one_allowed_collections": null,
				"one_collection": "directus_users",
				"one_collection_field": null,
				"one_deselect_action": "nullify",
				"one_field": null,
				"sort_field": null
			},
			"schema": {
				"table": "cm",
				"column": "user_created",
				"foreign_key_table": "directus_users",
				"foreign_key_column": "id",
				"constraint_name": "cm_user_created_foreign",
				"on_update": "NO ACTION",
				"on_delete": "NO ACTION"
			}
		},
		{
			"collection": "cm",
			"field": "user_updated",
			"related_collection": "directus_users",
			"meta": {
				"junction_field": null,
				"many_collection": "cm",
				"many_field": "user_updated",
				"one_allowed_collections": null,
				"one_collection": "directus_users",
				"one_collection_field": null,
				"one_deselect_action": "nullify",
				"one_field": null,
				"sort_field": null
			},
			"schema": {
				"table": "cm",
				"column": "user_updated",
				"foreign_key_table": "directus_users",
				"foreign_key_column": "id",
				"constraint_name": "cm_user_updated_foreign",
				"on_update": "NO ACTION",
				"on_delete": "NO ACTION"
			}
		},
		{
			"collection": "cm",
			"field": "responsible",
			"related_collection": "directus_users",
			"meta": {
				"junction_field": null,
				"many_collection": "cm",
				"many_field": "responsible",
				"one_allowed_collections": null,
				"one_collection": "directus_users",
				"one_collection_field": null,
				"one_deselect_action": "nullify",
				"one_field": null,
				"sort_field": null
			},
			"schema": {
				"table": "cm",
				"column": "responsible",
				"foreign_key_table": "directus_users",
				"foreign_key_column": "id",
				"constraint_name": "cm_responsible_foreign",
				"on_update": "NO ACTION",
				"on_delete": "SET NULL"
			}
		},
		{
			"collection": "cm",
			"field": "process",
			"related_collection": "process",
			"meta": {
				"junction_field": null,
				"many_collection": "cm",
				"many_field": "process",
				"one_allowed_collections": null,
				"one_collection": "process",
				"one_collection_field": null,
				"one_deselect_action": "nullify",
				"one_field": null,
				"sort_field": null
			},
			"schema": {
				"table": "cm",
				"column": "process",
				"foreign_key_table": "process",
				"foreign_key_column": "id",
				"constraint_name": "cm_process_foreign",
				"on_update": "NO ACTION",
				"on_delete": "SET NULL"
			}
		},
		{
			"collection": "cm",
			"field": "status",
			"related_collection": "process_status",
			"meta": {
				"junction_field": null,
				"many_collection": "cm",
				"many_field": "status",
				"one_allowed_collections": null,
				"one_collection": "process_status",
				"one_collection_field": null,
				"one_deselect_action": "nullify",
				"one_field": null,
				"sort_field": null
			},
			"schema": {
				"table": "cm",
				"column": "status",
				"foreign_key_table": "process_status",
				"foreign_key_column": "id",
				"constraint_name": "cm_status_foreign",
				"on_update": "NO ACTION",
				"on_delete": "SET NULL"
			}
		},
		{
			"collection": "task",
			"field": "user_updated",
			"related_collection": "directus_users",
			"meta": {
				"junction_field": null,
				"many_collection": "task",
				"many_field": "user_updated",
				"one_allowed_collections": null,
				"one_collection": "directus_users",
				"one_collection_field": null,
				"one_deselect_action": "nullify",
				"one_field": null,
				"sort_field": null
			},
			"schema": {
				"table": "task",
				"column": "user_updated",
				"foreign_key_table": "directus_users",
				"foreign_key_column": "id",
				"constraint_name": "task_user_updated_foreign",
				"on_update": "NO ACTION",
				"on_delete": "NO ACTION"
			}
		},
		{
			"collection": "task",
			"field": "user_created",
			"related_collection": "directus_users",
			"meta": {
				"junction_field": null,
				"many_collection": "task",
				"many_field": "user_created",
				"one_allowed_collections": null,
				"one_collection": "directus_users",
				"one_collection_field": null,
				"one_deselect_action": "nullify",
				"one_field": null,
				"sort_field": null
			},
			"schema": {
				"table": "task",
				"column": "user_created",
				"foreign_key_table": "directus_users",
				"foreign_key_column": "id",
				"constraint_name": "task_user_created_foreign",
				"on_update": "NO ACTION",
				"on_delete": "NO ACTION"
			}
		},
		{
			"collection": "task",
			"field": "responsible",
			"related_collection": "directus_users",
			"meta": {
				"junction_field": null,
				"many_collection": "task",
				"many_field": "responsible",
				"one_allowed_collections": null,
				"one_collection": "directus_users",
				"one_collection_field": null,
				"one_deselect_action": "nullify",
				"one_field": null,
				"sort_field": null
			},
			"schema": {
				"table": "task",
				"column": "responsible",
				"foreign_key_table": "directus_users",
				"foreign_key_column": "id",
				"constraint_name": "task_responsible_foreign",
				"on_update": "NO ACTION",
				"on_delete": "SET NULL"
			}
		},
		{
			"collection": "task",
			"field": "process",
			"related_collection": "process",
			"meta": {
				"junction_field": null,
				"many_collection": "task",
				"many_field": "process",
				"one_allowed_collections": null,
				"one_collection": "process",
				"one_collection_field": null,
				"one_deselect_action": "nullify",
				"one_field": null,
				"sort_field": null
			},
			"schema": {
				"table": "task",
				"column": "process",
				"foreign_key_table": "process",
				"foreign_key_column": "id",
				"constraint_name": "task_process_foreign",
				"on_update": "NO ACTION",
				"on_delete": "SET NULL"
			}
		},
		{
			"collection": "task",
			"field": "status",
			"related_collection": "task_status",
			"meta": {
				"junction_field": null,
				"many_collection": "task",
				"many_field": "status",
				"one_allowed_collections": null,
				"one_collection": "task_status",
				"one_collection_field": null,
				"one_deselect_action": "nullify",
				"one_field": null,
				"sort_field": null
			},
			"schema": {
				"table": "task",
				"column": "status",
				"foreign_key_table": "task_status",
				"foreign_key_column": "id",
				"constraint_name": "task_status_foreign",
				"on_update": "NO ACTION",
				"on_delete": "SET NULL"
			}
		},
		{
			"collection": "user_profile",
			"field": "user_updated",
			"related_collection": "directus_users",
			"meta": {
				"junction_field": null,
				"many_collection": "user_profile",
				"many_field": "user_updated",
				"one_allowed_collections": null,
				"one_collection": "directus_users",
				"one_collection_field": null,
				"one_deselect_action": "nullify",
				"one_field": null,
				"sort_field": null
			},
			"schema": {
				"table": "user_profile",
				"column": "user_updated",
				"foreign_key_table": "directus_users",
				"foreign_key_column": "id",
				"constraint_name": "user_profile_user_updated_foreign",
				"on_update": "NO ACTION",
				"on_delete": "NO ACTION"
			}
		},
		{
			"collection": "user_profile",
			"field": "user_created",
			"related_collection": "directus_users",
			"meta": {
				"junction_field": null,
				"many_collection": "user_profile",
				"many_field": "user_created",
				"one_allowed_collections": null,
				"one_collection": "directus_users",
				"one_collection_field": null,
				"one_deselect_action": "nullify",
				"one_field": null,
				"sort_field": null
			},
			"schema": {
				"table": "user_profile",
				"column": "user_created",
				"foreign_key_table": "directus_users",
				"foreign_key_column": "id",
				"constraint_name": "user_profile_user_created_foreign",
				"on_update": "NO ACTION",
				"on_delete": "NO ACTION"
			}
		},
		{
			"collection": "user_profile",
			"field": "user",
			"related_collection": "directus_users",
			"meta": {
				"junction_field": null,
				"many_collection": "user_profile",
				"many_field": "user",
				"one_allowed_collections": null,
				"one_collection": "directus_users",
				"one_collection_field": null,
				"one_deselect_action": "nullify",
				"one_field": null,
				"sort_field": null
			},
			"schema": {
				"table": "user_profile",
				"column": "user",
				"foreign_key_table": "directus_users",
				"foreign_key_column": "id",
				"constraint_name": "user_profile_user_foreign",
				"on_update": "NO ACTION",
				"on_delete": "NO ACTION"
			}
		}
	]
}